happy_vllm/__init__.py
happy_vllm/application.py
happy_vllm/launch.py
happy_vllm/utils.py
happy_vllm/utils_args.py
happy_vllm/core/__init__.py
happy_vllm/core/config.py
happy_vllm/core/logtools.py
happy_vllm/core/resources.py
happy_vllm/engine/__init__.py
happy_vllm/engine/mp_engine.py
happy_vllm/middlewares/__init__.py
happy_vllm/middlewares/exception.py
happy_vllm/model/__init__.py
happy_vllm/model/model_base.py
happy_vllm/routers/__init__.py
happy_vllm/routers/functional.py
happy_vllm/routers/technical.py
happy_vllm/routers/schemas/__init__.py
happy_vllm/routers/schemas/functional.py
happy_vllm/routers/schemas/technical.py
happy_vllm/routers/schemas/utils.py
happy_vllm/routers/schemas/examples/request.json
happy_vllm/routers/schemas/examples/response.json
happy_vllm-1.2.5.dist-info/licenses/LICENSE
happy_vllm-1.2.5.dist-info/METADATA
happy_vllm-1.2.5.dist-info/WHEEL
happy_vllm-1.2.5.dist-info/entry_points.txt
happy_vllm-1.2.5.dist-info/top_level.txt
happy_vllm-1.2.5.dist-info/RECORD
