Metadata-Version: 2.4
Name: happy_vllm
Version: 1.2.5
Summary: happy_vllm is a REST API for vLLM, production ready
Author: Agence Data Services FT
Author-email: drosdadssocle.00620@francetravail.fr
License: GNU AFFERO GENERAL PUBLIC LICENSE
Project-URL: Repository, https://github.com/France-Travail/happy_vllm
Project-URL: Documentation, https://france-travail.github.io/happy_vllm
Keywords: production,transformers,api-rest,serving,mlops,llm,llm-serving,vllm
Classifier: Programming Language :: Python :: 3
Classifier: Programming Language :: Python :: 3.10
Classifier: Programming Language :: Python :: 3.11
Requires-Python: <4.0,>=3.10
License-File: LICENSE
Requires-Dist: vllm[audio]<1.0,>=0.8.2
Requires-Dist: fastapi<1.0,>=0.115.12
Requires-Dist: pydantic_settings<3.0,>=2.8.1
Requires-Dist: uvicorn[standard]<1.0,>=0.34.0
Requires-Dist: prometheus_client<1.0,>=0.21.1
Requires-Dist: numpy<2.0,>=1.26.4
Provides-Extra: test
Requires-Dist: httpx<1.0,>=0.23; extra == "test"
Requires-Dist: pytest<9.0,>=8.2.0; extra == "test"
Requires-Dist: pytest-cov<6.0,>=5.0.0; extra == "test"
Requires-Dist: mypy<2.0,>=1.7.1; extra == "test"
Requires-Dist: pytest-asyncio<1.0,>=0.23.7; extra == "test"
Requires-Dist: asgi-lifespan<3.0.0,>=2.0.0; extra == "test"
Dynamic: license-file
